colimage/__init__.py
colimage/compare_img.py
colimage/get_pixel_value.py
colimage/read_exif.py
colimage/read_rawpy.py
colimage/srgb_to_lab.py
colimage/verify_ccm.py
colour_image_toolbox-0.0.3.dist-info/licenses/LICENSE
colour_image_toolbox-0.0.3.dist-info/METADATA
colour_image_toolbox-0.0.3.dist-info/WHEEL
colour_image_toolbox-0.0.3.dist-info/top_level.txt
colour_image_toolbox-0.0.3.dist-info/RECORD
